README.md
setup.py
JEMSVIDEOSDXL.egg-info/PKG-INFO
JEMSVIDEOSDXL.egg-info/SOURCES.txt
JEMSVIDEOSDXL.egg-info/dependency_links.txt
JEMSVIDEOSDXL.egg-info/requires.txt
JEMSVIDEOSDXL.egg-info/top_level.txt
stable_diffusion_videos/__init__.py
stable_diffusion_videos/app.py
stable_diffusion_videos/flax_stable_diffusion_pipeline.py
stable_diffusion_videos/image_generation.py
stable_diffusion_videos/stable_diffusion_pipeline.py
stable_diffusion_videos/upsampling.py
stable_diffusion_videos/utils.py