Metadata-Version: 2.1
Name: JEMSVIDEOSDXL
Version: 0.8.1
Summary: Create 🔥 videos with Stable Diffusion by exploring the latent space and morphing between text prompts.
Home-page: UNKNOWN
Author: JEM
Author-email: naterawdata@gmail.com
License: Apache
Platform: UNKNOWN
